image_shrinker/__init__.py
image_shrinker/shrinker.py
image_shrinker-0.1.0.dist-info/LICENSE
image_shrinker-0.1.0.dist-info/WHEEL
image_shrinker-0.1.0.dist-info/METADATA
image_shrinker-0.1.0.dist-info/RECORD
