Metadata-Version: 2.1
Name: image-shrinker
Version: 0.1.0
Summary: Shrinks images. Use it before committing to git and/or using on a website
Keywords: image,shrink,web
Author-email: Don Parakin <don@weaddvalue.ca>
Requires-Python: >=3.8
Classifier: Programming Language :: Python :: 3
Classifier: License :: OSI Approved :: MIT License
Classifier: Operating System :: OS Independent
Classifier: Topic :: Multimedia :: Graphics
Requires-Dist: Pillow>3.0.0
Project-URL: Documentation, https://image-shrinker.readthedocs.org
Project-URL: Homepage, https://gitlab.com/parakin/image-shrinker
Project-URL: Issues, https://gitlab.com/parakin/image-shrinker/-/issues
Project-URL: Repository, https://gitlab.com/parakin/image-shrinker.git
